cython_fortran_file/__init__.py
cython_fortran_file/cython_fortran_utils.cpython-39-x86_64-linux-gnu.so
cython_fortran_file-0.2.7.dist-info/RECORD
cython_fortran_file-0.2.7.dist-info/METADATA
cython_fortran_file-0.2.7.dist-info/WHEEL
cython_fortran_file-0.2.7.dist-info/top_level.txt
cython_fortran_file-0.2.7.dist-info/LICENSE
