Metadata-Version: 2.1
Name: cython_fortran_file
Version: 0.2.7
Summary: An efficient package to read fortran-record files in Python.
Author-email: Corentin Cadiou <contact@cphyc.me>
License: MIT
Project-URL: Homepage, https://github.com/cphyc/cython_fortran_file
Classifier: Development Status :: 4 - Beta
Classifier: License :: OSI Approved :: MIT License
Classifier: Programming Language :: Cython
Classifier: Programming Language :: Python
Classifier: Programming Language :: Python :: 3
Classifier: Programming Language :: Python :: 3 :: Only
Classifier: Topic :: Utilities
Requires-Python: >=3.9
License-File: LICENSE
Requires-Dist: cython
Requires-Dist: numpy
